kong_admin
