Metadata-Version: 1.0
Name: kong-admin
Version: 0.0.2
Summary: A kong admin api sdk.
Home-page: https://github.com/codeif/kong-admin
Author: codeif
Author-email: me@codeif.com
License: MIT
Platform: UNKNOWN
